LICENSE
MANIFEST.in
README.md
requirements.txt
setup.py
bosun_foscam_plugins/__init__.py
bosun_foscam_plugins.egg-info/PKG-INFO
bosun_foscam_plugins.egg-info/SOURCES.txt
bosun_foscam_plugins.egg-info/dependency_links.txt
bosun_foscam_plugins.egg-info/not-zip-safe
bosun_foscam_plugins.egg-info/requires.txt
bosun_foscam_plugins.egg-info/top_level.txt
bosun_foscam_plugins/devices/__init__.py
bosun_foscam_plugins/devices/h264.py
bosun_foscam_plugins/devices/mjpeg.py