Metadata-Version: 1.0
Name: bosun-foscam-plugins
Version: 0.1.0
Summary: Bosun plugins for the Foscam camera series to work with crowsnest.io
Home-page: https://github.com/crowsnest-io/bosun-foscam-plugins
Author: Ian A Wilson, Alex Karpinski, Michael Kruk
Author-email: UNKNOWN
License: UNKNOWN
Platform: UNKNOWN
Classifier: Environment :: No Input/Output (Daemon)
Classifier: License :: OSI Approved :: MIT License
Classifier: Natural Language :: English
Classifier: Operating System :: Unix
Classifier: Programming Language :: Python
Classifier: Topic :: Multimedia
